slidev2pptx/__init__.py
slidev2pptx/cli.py
slidev2pptx-0.1.0.dist-info/LICENSE
slidev2pptx-0.1.0.dist-info/METADATA
slidev2pptx-0.1.0.dist-info/WHEEL
slidev2pptx-0.1.0.dist-info/entry_points.txt
slidev2pptx-0.1.0.dist-info/RECORD
