Metadata-Version: 2.1
Name: slidev2pptx
Version: 0.1.0
Summary: 
Author: Yu Zhang
Author-email: yuzhang94@outlook.com
Requires-Python: >=3.10,<4.0
Classifier: Programming Language :: Python :: 3
Classifier: Programming Language :: Python :: 3.10
Classifier: Programming Language :: Python :: 3.11
Classifier: Programming Language :: Python :: 3.12
Requires-Dist: click (>=8.1.7,<9.0.0)
Requires-Dist: pillow (>=10.3.0,<11.0.0)
Requires-Dist: python-pptx (>=0.6.23,<0.7.0)
